ha4t/__init__.py
ha4t/api.py
ha4t/config.py
ha4t/orc.py
ha4t/aircv/__init__.py
ha4t/aircv/aircv.py
ha4t/aircv/cal_confidence.py
ha4t/aircv/cv.py
ha4t/aircv/error.py
ha4t/aircv/keypoint_base.py
ha4t/aircv/keypoint_matching.py
ha4t/aircv/keypoint_matching_contrib.py
ha4t/aircv/multiscale_template_matching.py
ha4t/aircv/resolution.py
ha4t/aircv/settings.py
ha4t/aircv/sift.py
ha4t/aircv/template.py
ha4t/aircv/template_matching.py
ha4t/aircv/transform.py
ha4t/aircv/utils.py
ha4t/binaries/ios_webkit_debug_proxy.exe
ha4t/binaries/libcrypto-3-x64.dll
ha4t/binaries/libimobiledevice-1.0.dll
ha4t/binaries/libimobiledevice-glue-1.0.dll
ha4t/binaries/libpcre-1.dll
ha4t/binaries/libpcreposix-0.dll
ha4t/binaries/libplist-2.0.dll
ha4t/binaries/libssl-3-x64.dll
ha4t/binaries/libusbmuxd-2.0.dll
ha4t/binaries/remotedebug_ios_webkit_adapter.exe
ha4t/cdp/__init__.py
ha4t/cdp/by.py
ha4t/cdp/cdp.py
ha4t/cdp/jsCode.py
ha4t/cdp/server.py
ha4t/utils/__init__.py
ha4t/utils/decorator_utils.py
ha4t/utils/files_operat.py
ha4t/utils/log_utils.py
ha4t/utils/paths.py
HA4T-0.0.7.dist-info/LICENSE
HA4T-0.0.7.dist-info/METADATA
HA4T-0.0.7.dist-info/WHEEL
HA4T-0.0.7.dist-info/top_level.txt
HA4T-0.0.7.dist-info/RECORD
