Metadata-Version: 2.1
Name: HA4T
Version: 0.0.7
Summary: 跨平台的UI自动化框架，适用于混合型app
Home-page: https://github.com/exuils/HA4T
Author: caishilong
Author-email: caishilong@exuils.com
License: Apache License 2.0
Keywords: automation,automated-test,game,android,ios,hybrid-app
Classifier: Programming Language :: Python :: 3
Classifier: License :: OSI Approved :: MIT License
Classifier: Operating System :: OS Independent
Requires-Python: >=3.7
License-File: LICENSE
Requires-Dist: colorlog ~=6.8.2
Requires-Dist: pillow ~=10.4.0
Requires-Dist: requests ~=2.32.3
Requires-Dist: uiautomator2 ~=3.2.2
Requires-Dist: websockets ~=10.4
Requires-Dist: numpy ~=1.26.4
Requires-Dist: paddleocr ~=2.8.1
Requires-Dist: setuptools ~=73.0.1
Requires-Dist: six ~=1.16.0
Requires-Dist: wheel ~=0.43.0
Requires-Dist: tornado ~=6.4.1
Requires-Dist: logzero ~=1.7.0
Requires-Dist: logging-reset
Requires-Dist: adbutils ~=2.7.2
Requires-Dist: facebook-wda
Requires-Dist: paddlepaddle
Requires-Dist: paddleocr
Requires-Dist: tidevice
Requires-Dist: deepdiff ~=7.0.1
Requires-Dist: opencv-python ~=4.10.0.84
Requires-Dist: matplotlib ~=3.9.2
Requires-Dist: pytest ~=8.3.3
Requires-Dist: psutil ~=6.1.0
Requires-Dist: mock ~=5.1.0
Requires-Dist: allure-pytest
Requires-Dist: pywin32
Provides-Extra: dev
Requires-Dist: flake8 ; extra == 'dev'
Requires-Dist: black ==22.3.0 ; extra == 'dev'
Requires-Dist: isort ; extra == 'dev'
Requires-Dist: twine ; extra == 'dev'
Requires-Dist: pytest ; extra == 'dev'
Requires-Dist: wheel ; extra == 'dev'
